modelLab/__init__.py
modelLab/initial_checks.py
modelLab/Classification/__init__.py
modelLab/Classification/classification.py
modelLab/Classification/classification_metrics.py
modelLab/Regression/__init__.py
modelLab/Regression/regression.py
modelLab/Regression/regression_metrics.py
modelLab-0.3.4.dist-info/LICENSE
modelLab-0.3.4.dist-info/METADATA
modelLab-0.3.4.dist-info/WHEEL
modelLab-0.3.4.dist-info/top_level.txt
modelLab-0.3.4.dist-info/RECORD
