Metadata-Version: 2.1
Name: modelLab
Version: 0.3.4
Summary: A lib for automating model training process of choosing best model that works for you data
Home-page: https://github.com/Abhishekkaddipudi/modelLab
Author: Abhishek Kaddipudi
Author-email: abhishekkaddipudi007@gmail.com
Keywords: automl,model,modelbuilder,modelLab
Classifier: Development Status :: 3 - Alpha
Classifier: License :: OSI Approved :: MIT License
Classifier: Operating System :: OS Independent
Classifier: Programming Language :: Python
Classifier: Programming Language :: Python :: 3
Classifier: Programming Language :: Python :: 3.9
Classifier: Programming Language :: Python :: 3.11
Classifier: Topic :: Software Development :: Libraries :: Python Modules
License-File: LICENSE
Requires-Dist: scikit-learn
Requires-Dist: xgboost
Requires-Dist: catboost
Requires-Dist: lightgbm
